MANIFEST.in
README.md
setup.cfg
setup.py
versioneer.py
pygments_tiger/__init__.py
pygments_tiger/_version.py
pygments_tiger.egg-info/PKG-INFO
pygments_tiger.egg-info/SOURCES.txt
pygments_tiger.egg-info/dependency_links.txt
pygments_tiger.egg-info/entry_points.txt
pygments_tiger.egg-info/requires.txt
pygments_tiger.egg-info/top_level.txt