Metadata-Version: 1.0
Name: pygments-tiger
Version: 1.6
Summary: Pygments lexer for the Tiger Language
Home-page: https://github.com/lse/pygments-tiger
Author: Gabriel Laskar
Author-email: gabriel@lse.epita.fr
License: MIT
Platform: UNKNOWN
